tempun/__init__.py
tempun-0.2.4.dist-info/licenses/LICENSE
tempun-0.2.4.dist-info/METADATA
tempun-0.2.4.dist-info/PKG-INFO (1)
tempun-0.2.4.dist-info/WHEEL
tempun-0.2.4.dist-info/top_level.txt
tempun-0.2.4.dist-info/RECORD
