Metadata-Version: 2.4
Name: tempun
Version: 0.2.4
Summary: A package to deal with temporal uncertainty in historical/archaeological datasets
Home-page: https://github.com/sdam-au/sddk
Author: Vojtech Kase
Author-email: vojtech.kase@gmail.com
Classifier: Programming Language :: Python :: 3
Classifier: License :: OSI Approved :: MIT License
Classifier: Operating System :: OS Independent
Requires-Python: >=3.4
License-File: LICENSE
Requires-Dist: pandas
Requires-Dist: numpy
Requires-Dist: scipy
Requires-Dist: matplotlib
Dynamic: author
Dynamic: author-email
Dynamic: classifier
Dynamic: description
Dynamic: description-content-type
Dynamic: home-page
Dynamic: license-file
Dynamic: requires-dist
Dynamic: requires-python
Dynamic: summary
